coipee/__init__.py
coipee/artifacts.py
coipee/detectors/__init__.py
coipee/explanations/__init__.py
coipee/generators/__init__.py
coipee/generators/base.py
coipee/generators/gaussian.py
coipee-0.0.2.dist-info/METADATA
coipee-0.0.2.dist-info/WHEEL
coipee-0.0.2.dist-info/licenses/LICENSE
coipee-0.0.2.dist-info/RECORD
