Metadata-Version: 2.3
Name: coipee
Version: 0.0.2
Summary: Demo of a Caipi-like system for explanatory interactive learning.
Project-URL: Homepage, https://github.com/msetzu/coipee
Project-URL: Bug Tracker, https://github.com/msetzu/coipee
Author-email: Mattia Setzu <mattia.setzu@unipi.it>
License-File: LICENSE
Classifier: Development Status :: 2 - Pre-Alpha
Classifier: Intended Audience :: Developers
Classifier: License :: OSI Approved :: GNU General Public License v3 or later (GPLv3+)
Classifier: Operating System :: OS Independent
Classifier: Programming Language :: Python :: 3.12
Requires-Python: <=3.13,>3.10
Requires-Dist: cloudpickle==3.0.0
Requires-Dist: joblib==1.4.2
Requires-Dist: llvmlite==0.42.0
Requires-Dist: numba==0.59.1
Requires-Dist: numpy==1.26.4
Requires-Dist: packaging==24.0
Requires-Dist: pandas==2.2.2
Requires-Dist: python-dateutil==2.9.0.post0
Requires-Dist: pytz==2024.1
Requires-Dist: scikit-learn==1.5.0
Requires-Dist: scipy==1.13.1
Requires-Dist: shap==0.45.1
Requires-Dist: six==1.16.0
Requires-Dist: slicer==0.0.8
Requires-Dist: threadpoolctl==3.5.0
Requires-Dist: tqdm==4.66.4
Requires-Dist: tzdata==2024.1
